sider_captcha_solver.py
configs/config.yaml
configs/train_config.yaml
scripts/download_images.py
scripts/generate_captchas.py
scripts/split_dataset.py
scripts/annotation/annotate_captchas_matplotlib.py
scripts/annotation/annotate_captchas_web.py
scripts/data_generation/geometry_generator.py
scripts/data_generation/puzzle_background_generator.py
scripts/evaluation/evaluate_model.py
scripts/training/analyze_training.py
scripts/training/dataset.py
scripts/training/train.py
sider_captcha_solver-1.0.3.dist-info/licenses/LICENSE
src/__init__.py
src/captcha_generator/__init__.py
src/captcha_generator/batch_generator.py
src/captcha_generator/lighting_effects.py
src/captcha_generator/simple_puzzle_generator.py
src/captcha_generator/slider_effects.py
src/checkpoints/1.0.2/best_model.pth
src/checkpoints/1.0.3/best_model.pth
src/data_collection/__init__.py
src/data_collection/pixabay_downloader.py
src/models/__init__.py
src/models/captcha_solver.py
src/models/centernet_heads.py
src/models/losses.py
src/models/predictor.py
src/models/resnet18_lite.py
src/utils/__init__.py
src/utils/logger.py
tests/benchmark_inference.py
tests/merge_real_captchas.py
tests/test_all_puzzle_shapes.py
tests/test_brightness_darkness_levels.py
tests/test_captcha_generation.py
tests/test_confusing_gap.py
tests/test_darkness_levels.py
tests/test_distance_error_visualization.py
tests/test_generate_captchas.py
tests/test_model_architecture.py
tests/test_real_captchas.py
tests/test_rotated_gap.py
tests/test_slider_effects.py
tests/test_slider_perlin_noise.py
sider_captcha_solver-1.0.3.dist-info/METADATA
sider_captcha_solver-1.0.3.dist-info/WHEEL
sider_captcha_solver-1.0.3.dist-info/entry_points.txt
sider_captcha_solver-1.0.3.dist-info/top_level.txt
sider_captcha_solver-1.0.3.dist-info/RECORD
