Metadata-Version: 2.4
Name: sider-captcha-solver
Version: 1.0.3
Summary: Industrial-grade slider CAPTCHA recognition system based on deep learning
Home-page: https://github.com/TomokotoKiyoshi/Sider_CAPTCHA_Solver
Author: TomokotoKiyoshi
Author-email: 
Maintainer: TomokotoKiyoshi
License: MIT
Project-URL: Homepage, https://github.com/TomokotoKiyoshi/Sider_CAPTCHA_Solver
Project-URL: Documentation, https://github.com/TomokotoKiyoshi/Sider_CAPTCHA_Solver/blob/main/README.md
Project-URL: Repository, https://github.com/TomokotoKiyoshi/Sider_CAPTCHA_Solver
Project-URL: Issues, https://github.com/TomokotoKiyoshi/Sider_CAPTCHA_Solver/issues
Keywords: captcha,slider,recognition,deep-learning,pytorch,centernet,computer-vision
Classifier: Development Status :: 4 - Beta
Classifier: Intended Audience :: Developers
Classifier: Intended Audience :: Science/Research
Classifier: License :: OSI Approved :: MIT License
Classifier: Operating System :: OS Independent
Classifier: Programming Language :: Python :: 3
Classifier: Programming Language :: Python :: 3.8
Classifier: Programming Language :: Python :: 3.9
Classifier: Programming Language :: Python :: 3.10
Classifier: Programming Language :: Python :: 3.11
Classifier: Topic :: Scientific/Engineering :: Artificial Intelligence
Classifier: Topic :: Scientific/Engineering :: Image Recognition
Classifier: Topic :: Software Development :: Libraries :: Python Modules
Requires-Python: >=3.8
License-File: LICENSE
Requires-Dist: torch>=2.0.0
Requires-Dist: torchvision>=0.15.0
Requires-Dist: opencv-python>=4.5.0
Requires-Dist: Pillow>=9.0.0
Requires-Dist: numpy>=1.20.0
Requires-Dist: matplotlib>=3.5.0
Requires-Dist: tqdm>=4.60.0
Requires-Dist: PyYAML>=6.0
Requires-Dist: requests>=2.25.0
Requires-Dist: aiohttp>=3.8.0
Requires-Dist: loguru>=0.6.0
Requires-Dist: pandas>=1.3.0
Requires-Dist: seaborn>=0.11.0
Requires-Dist: psutil>=5.8.0
Requires-Dist: fastapi>=0.70.0
Requires-Dist: uvicorn>=0.15.0
Dynamic: home-page
Dynamic: license-file
Dynamic: requires-python
